seagen.py
seagen-1.5.dist-info/LICENSE.txt
seagen-1.5.dist-info/METADATA
seagen-1.5.dist-info/WHEEL
seagen-1.5.dist-info/top_level.txt
seagen-1.5.dist-info/RECORD
