Metadata-Version: 2.1
Name: seagen
Version: 1.5
Summary: Stretched Equal Area Generator
Home-page: https://github.com/jkeger/seagen
Author: Jacob Kegerreis
Author-email: jacob.kegerreis@durham.ac.uk
License: GNU GPLv3+
Project-URL: Paper, https://doi.org/10.1093/mnras/stz1606
Project-URL: Group, http://icc.dur.ac.uk/giant_impacts
Project-URL: WoMa, https://github.com/srbonilla/WoMa
Keywords: particle arrangement density sphere shell SPH initial conditions
Platform: UNKNOWN
Classifier: Programming Language :: Python :: 3
Classifier: License :: OSI Approved :: GNU General Public License v3 or later (GPLv3+)
Classifier: Development Status :: 4 - Beta
Requires-Python: >=3
Requires-Dist: numpy
